p67_awstools/cli_scale_ec2_asg.py
p67_awstools/password_rotate.py
p67_awstools-0.1.2.dist-info/METADATA
p67_awstools-0.1.2.dist-info/WHEEL
p67_awstools-0.1.2.dist-info/entry_points.txt
p67_awstools-0.1.2.dist-info/RECORD
