Metadata-Version: 2.1
Name: p67-awstools
Version: 0.1.2
Summary: Various AWS code
Author: Rene Benner
Author-email: rene@fortytwo.nl
Requires-Python: >=3.9,<4.0
Classifier: Programming Language :: Python :: 3
Classifier: Programming Language :: Python :: 3.9
Classifier: Programming Language :: Python :: 3.10
Classifier: Programming Language :: Python :: 3.11
Requires-Dist: boto3 (>=1.26.134,<2.0.0)
